{
  "issue": {
    "date": "2010",
    "issue_id": 352,
    "introductory_text": "",
    "name": "2010 January - December Submissions",
    "publications": [
      695,
      708,
      709,
      710,
      711,
      712,
      713,
      715,
      716,
      718,
      719,
      720,
      724,
      725,
      726,
      764,
      765,
      766,
      767,
      772,
      781
    ],
    "short_description": "Yearly submissions in support of the VTK community representing a collection of proposed and implemented algorithms, documented features, and case studies."
  }
}