{
  "issue": {
    "issue_id": 350,
    "introductory_text": "Papers, data, and reviews from the Insight Journal.",
    "name": "2009 July-December",
    "publications": [
      646,
      662,
      673,
      676,
      680,
      681,
      682,
      687,
      688,
      692,
      693,
      694,
      696,
      698,
      700,
      701,
      702,
      704,
      705,
      706,
      707
    ],
    "short_description": "Open-source items submitted to the IJ between July and December 2009"
  }
}