{
  "publication": {
    "abstract": "This paper describes a new tutorial book titled \"An Introduction to Programming for Medical Image Analysis with the Visualization Toolkit.\" This book derived from a set of class handouts used in a biomedical engineering graduate seminar at Yale University. The goal for the seminar was to\r\nintroduce the students to the Visualization Toolkit (VTK) and, to a lesser extent, the Insight Toolkit (ITK). A draft version of the complete book (including all the sample code) is available online at www.bioimagesuite.org/vtkbook.",
    "authors": [
      {
        "author_fullname": "Papademetris, Xenophon",
        "author_place": 1,
        "persona_email": "xenophon.papademetris@yale.edu",
        "persona_firstname": "Xenophon",
        "persona_id": 79,
        "persona_lastname": "Papademetris"
      }
    ],
    "categories": [],
    "comments": [],
    "date_submitted": "2006-12-13T16:20:57Z",
    "journals": [
      {
        "journal_id": 3,
        "journal_name": "The Insight Journal"
      }
    ],
    "license": "You are licensing your work to Kitware Inc. under the\nCreative Commons Attribution License Version 3.0.\n\nKitware Inc. agrees to the following:\n\nKitware is free\n * to copy, distribute, display, and perform the work\n * to make derivative works\n * to make commercial use of the work\n\nUnder the following conditions:\n\\\"by Attribution\\\" - Kitware must attribute the work in the manner specified by the author or licensor.\n\n * For any reuse or distribution, they must make clear to others the license terms of this work.\n * Any of these conditions can be waived if they get permission from the copyright holder.\n\nYour fair use and other rights are in no way affected by the above.\n\nThis is a human-readable summary of the Legal Code (the full license) available at\nhttp://creativecommons.org/licenses/by/3.0/legalcode",
    "publication_id": 137,
    "reviews": [],
    "revisions": [
      {
        "article": "bafkreigf6msqpvslkjk3vdadgvmm6qq2xju43jyip2ghtraaqyj3d32rze",
        "citation_list": [
          {
            "key": "ref1",
            "score": 57.580936,
            "unstructured": "An integrated medical image analysis suite: An update+In ISC/NA-MIC Workshop on Open Science at MICCAI+1926+X. Papademetris+M. Jackowski+N. Rajeevan+R. T. Constable+L. H. Staib. BioImage Suite"
          },
          {
            "doi": "10.1016/b978-012387582-2/50003-4",
            "key": "ref2",
            "score": 78.102844,
            "unstructured": "The Visualization Toolkit: An Object-Oriented Approach to 3D Graphics. Kitware, Inc+2003+W. Schroeder+K. Martin+and B. Lorensen+I Part"
          },
          {
            "key": "ref3",
            "score": 9.669355,
            "unstructured": "Introduction ......................................................8"
          },
          {
            "key": "ref4",
            "score": 43.161156,
            "unstructured": "Programming with Tcl/Tk+Revision Control+With Subversion ................................. Part+II"
          },
          {
            "key": "ref5",
            "score": 25.306091,
            "unstructured": "Tcl ..............................................19"
          },
          {
            "key": "ref6",
            "score": 21.94858,
            "unstructured": "Tcl ...........................................27"
          },
          {
            "key": "ref7",
            "score": 26.37259,
            "unstructured": "An Introduction+To Tk ............................................35"
          },
          {
            "key": "ref8",
            "score": 21.251183,
            "unstructured": "II .......................................................43 Tk Part"
          },
          {
            "key": "ref9",
            "score": 47.639423,
            "unstructured": "Programming with+Object Oriented+Tcl ....................53"
          },
          {
            "key": "ref10",
            "score": 39.004684,
            "unstructured": "The Visualization Toolkit I - Using Tcl+GUIs ................................... Iwidgets: Object Oriented+III Part"
          },
          {
            "key": "ref11",
            "score": 27.721355,
            "unstructured": "9. An Introduction to the Visualization+Toolkit .....................71"
          },
          {
            "key": "ref12",
            "score": 19.584354,
            "unstructured": "VTK .......................................76"
          },
          {
            "key": "ref13",
            "score": 19.584354,
            "unstructured": "VTK ....................................................86"
          },
          {
            "key": "ref14",
            "score": 19.584354,
            "unstructured": "VTK .........................................93"
          },
          {
            "key": "ref15",
            "score": 18.528118,
            "unstructured": "Transformations .................................................105"
          },
          {
            "key": "ref16",
            "score": 27.566029,
            "unstructured": "Interfacing To BioImage Suite using Tcl+VTK Classes ..................................... Some Additional+IV Part"
          },
          {
            "key": "ref17",
            "score": 25.28866,
            "unstructured": "Components ............................122 Leveraging BioImage Suite"
          },
          {
            "key": "ref18",
            "score": 32.099525,
            "unstructured": "Writing your own BioImage Suite+Application ....................."
          },
          {
            "key": "ref19",
            "score": 26.052044,
            "unstructured": "Compiling with CMAKE .............................147 Cross-Platform"
          },
          {
            "key": "ref20",
            "score": 39.16871,
            "unstructured": "VTK Programming with C+++VTK .......................................... Part+VI"
          },
          {
            "key": "ref21",
            "score": 27.086246,
            "unstructured": "+ .+Extending VTK using C++........................................167"
          },
          {
            "key": "ref22",
            "score": 30.58999,
            "unstructured": "Point-based Registration with ICP+...............................179"
          },
          {
            "key": "ref23",
            "score": 24.796679,
            "unstructured": "Based Segmentation ....................................197 Intensity"
          },
          {
            "key": "ref24",
            "score": 27.993828,
            "unstructured": "A Templated Image to Image+Filter ...............................215"
          },
          {
            "key": "ref25",
            "score": 28.170471,
            "unstructured": "Data Objects ............................................222 Copying"
          },
          {
            "key": "ref26",
            "score": 22.261105,
            "unstructured": "Insight Toolkit .............................................226 The"
          }
        ],
        "dapp": null,
        "dataset": null,
        "doi": "10.54294/gf96ro",
        "handle": "1926/395",
        "source_code": null,
        "source_code_git_ref": null
      }
    ],
    "source_code_git_repo": null,
    "submitted_by_author": {
      "author_email": "xenophon.papademetris@yale.edu",
      "author_firstname": "Xenophon",
      "author_fullname": "Papademetris, Xenophon",
      "author_id": 79,
      "author_institution": "Yale University",
      "author_lastname": "Papademetris"
    },
    "tags": [
      "VTK",
      "Tutorial"
    ],
    "title": "Medical Image Analysis with VTK: A Tutorial"
  }
}